Metadata-Version: 2.1
Name: toga-falcon
Version: 0.0.0
Summary: A Falcon backend for the Toga widget toolkit.
Home-page: https://beeware.org/project/projects/libraries/toga/
Author: Russell Keith-Magee
Author-email: russell@keith-magee.com
Maintainer: BeeWare Team
Maintainer-email: team@beeware.org
License: New BSD
Project-URL: Funding, https://beeware.org/contributing/membership/
Project-URL: Documentation, http://toga.readthedocs.io/en/latest/
Project-URL: Tracker, https://github.com/beeware/toga/issues
Project-URL: Source, https://github.com/beeware/toga
Keywords: gui,widget,cross-platform,toga,web,falcon
Platform: UNKNOWN
Classifier: Development Status :: 3 - Alpha
Classifier: Intended Audience :: Developers
Classifier: License :: OSI Approved :: BSD License
Classifier: Operating System :: OS Independent
Classifier: Programming Language :: Python :: 3
Classifier: Programming Language :: Python :: 3.5
Classifier: Programming Language :: Python :: 3.6
Classifier: Programming Language :: Python :: 3.7
Classifier: Programming Language :: Python :: 3.8
Classifier: Programming Language :: Python :: 3 :: Only
Classifier: Topic :: Software Development
Classifier: Topic :: Software Development :: User Interfaces
Classifier: Topic :: Software Development :: Widget Sets
Requires-Python: >=3.5
